llm_utils/__init__.py
llm_utils/group_messages.py
llm_utils/llm_ray.py
llm_utils/chat_format/__init__.py
llm_utils/chat_format/display.py
llm_utils/chat_format/transform.py
llm_utils/chat_format/utils.py
llm_utils/lm/__init__.py
llm_utils/lm/base_prompt_builder.py
llm_utils/lm/llm.py
llm_utils/lm/llm_signature.py
llm_utils/lm/lm_base.py
llm_utils/lm/mixins.py
llm_utils/lm/openai_memoize.py
llm_utils/lm/signature.py
llm_utils/lm/utils.py
llm_utils/lm/async_lm/__init__.py
llm_utils/lm/async_lm/_utils.py
llm_utils/lm/async_lm/async_llm_task.py
llm_utils/lm/async_lm/async_lm.py
llm_utils/lm/async_lm/async_lm_base.py
llm_utils/lm/async_lm/lm_specific.py
llm_utils/scripts/README.md
llm_utils/scripts/fast_vllm.py
llm_utils/scripts/vllm_load_balancer.py
llm_utils/scripts/vllm_serve.py
llm_utils/vector_cache/__init__.py
llm_utils/vector_cache/cli.py
llm_utils/vector_cache/core.py
llm_utils/vector_cache/types.py
llm_utils/vector_cache/utils.py
speedy_utils/__imports.py
speedy_utils/__init__.py
speedy_utils/common/__init__.py
speedy_utils/common/clock.py
speedy_utils/common/function_decorator.py
speedy_utils/common/logger.py
speedy_utils/common/notebook_utils.py
speedy_utils/common/patcher.py
speedy_utils/common/report_manager.py
speedy_utils/common/utils_cache.py
speedy_utils/common/utils_error.py
speedy_utils/common/utils_io.py
speedy_utils/common/utils_misc.py
speedy_utils/common/utils_print.py
speedy_utils/multi_worker/__init__.py
speedy_utils/multi_worker/_multi_process.py
speedy_utils/multi_worker/_multi_process_ray.py
speedy_utils/multi_worker/common.py
speedy_utils/multi_worker/dataset_ray.py
speedy_utils/multi_worker/dataset_sharding.py
speedy_utils/multi_worker/parallel_gpu_pool.py
speedy_utils/multi_worker/process.py
speedy_utils/multi_worker/progress.py
speedy_utils/multi_worker/thread.py
speedy_utils/scripts/__init__.py
speedy_utils/scripts/kill_mpython.py
speedy_utils/scripts/mpython.py
speedy_utils/scripts/openapi_client_codegen.py
vision_utils/README.md
speedy_utils-1.1.47.dist-info/METADATA
speedy_utils-1.1.47.dist-info/WHEEL
speedy_utils-1.1.47.dist-info/entry_points.txt
speedy_utils-1.1.47.dist-info/RECORD
