Metadata-Version: 2.4
Name: speedy-utils
Version: 1.1.47
Summary: Fast and easy-to-use package for data science
Project-URL: Homepage, https://github.com/anhvth/speedy
Project-URL: Repository, https://github.com/anhvth/speedy
Author-email: AnhVTH <anhvth.226@gmail.com>
License: MIT
Classifier: Development Status :: 4 - Beta
Classifier: Intended Audience :: Developers
Classifier: License :: OSI Approved :: MIT License
Classifier: Programming Language :: Python :: 3
Classifier: Programming Language :: Python :: 3.8
Classifier: Programming Language :: Python :: 3.9
Classifier: Programming Language :: Python :: 3.10
Classifier: Programming Language :: Python :: 3.11
Classifier: Programming Language :: Python :: 3.12
Classifier: Programming Language :: Python :: 3.13
Classifier: Programming Language :: Python :: 3.14
Requires-Python: >=3.9
Requires-Dist: aiohttp
Requires-Dist: bump2version
Requires-Dist: cachetools
Requires-Dist: debugpy
Requires-Dist: fastcore
Requires-Dist: fastprogress
Requires-Dist: freezegun
Requires-Dist: ipdb
Requires-Dist: ipywidgets
Requires-Dist: json-repair
Requires-Dist: jupyterlab
Requires-Dist: loguru
Requires-Dist: matplotlib
Requires-Dist: numpy
Requires-Dist: openai
Requires-Dist: packaging
Requires-Dist: pandas
Requires-Dist: pydantic
Requires-Dist: pytest
Requires-Dist: ray
Requires-Dist: requests
Requires-Dist: rich>=14.3.1
Requires-Dist: ruff
Requires-Dist: scikit-learn
Requires-Dist: tabulate
Requires-Dist: tqdm
Requires-Dist: xxhash
Provides-Extra: ray
Requires-Dist: ray[data,llm]>=2.40.0; extra == 'ray'
Requires-Dist: vllm>=0.6.3; extra == 'ray'
